{"ti.ui.defaultunit":"dp","appc-app-id":"57488b222b876e477d5cef3b","acs-authbase-url-development":"https://secure-identity.cloud.appcelerator.com","acs-base-url-development":"https://api.cloud.appcelerator.com","acs-oauth-secret-development":"O9XLzvW6KLCBLA3TuMLErQq8tDf1jHB0","acs-oauth-key-development":"poT9kT7KB3CLGcyeyk9dMpQYNw1Rxger","acs-api-key-development":"epwoYJfgd7pVL01PMZADyJIlMzbgsrTX","acs-username-development":"appc_app_user_dev","acs-password-development":"834NSQh5qmZ2dUqtJx","acs-authbase-url-production":"https://secure-identity.cloud.appcelerator.com","acs-base-url-production":"https://api.cloud.appcelerator.com","acs-oauth-secret-production":"JjHCng76UUbNK6VM5NBmBXRdItBO95wM","acs-oauth-key-production":"UJFMUcITSrbYaxwfDuj8T5e6or8Y6g14","acs-api-key-production":"XxqlzYpUqeIDZVbiE9L38qh7zYvE87LC","acs-username-production":"appc_app_user","acs-password-production":"xQaQG4cYz8OHByhM2z","appc-org-id":"100109396","appc-creator-user-id":"d830e65d-346d-48f8-97bb-ee39e5323ec2","ti.deploytype":"test"}